{
  "registros": [
    {
      "valor": 455,
      "caja": "ingreso",
      "id": "2"
    },
    {
      "valor": 4545,
      "caja": "egreso",
      "id": "4"
    },
    {
      "valor": 7855,
      "caja": "ingreso",
      "id": "7"
    },
    {
      "valor": 54654684,
      "caja": "ingreso",
      "id": "12"
    },
    {
      "valor": 87878,
      "caja": "egreso",
      "id": "15"
    },
    {
      "valor": 9879,
      "caja": "egreso",
      "id": "16"
    },
    {
      "valor": 8484,
      "caja": "egreso",
      "id": "17"
    }
  ]
}